gazoo/__init__.py
gazoo/backup_file.py
gazoo/backup_worker.py
gazoo/cleanup_worker.py
gazoo/config.py
gazoo/util.py
gazoo/worker_status.py
gazoo/wrapper.py
gazoo-0.0.2.dist-info/entry_points.txt
gazoo-0.0.2.dist-info/LICENSE.md
gazoo-0.0.2.dist-info/WHEEL
gazoo-0.0.2.dist-info/METADATA
gazoo-0.0.2.dist-info/RECORD
