Metadata-Version: 2.1
Name: gazoo
Version: 0.0.2
Summary: Wrap Minecraft bedrock server to make proper backups.
Home-page: https://gitlab.com/thesmiley1/gazoo
License: MIT
Keywords: minecraft,bedrock
Author: John Schroeder
Author-email: john@schroedernet.software
Requires-Python: >=3.8,<4.0
Classifier: License :: OSI Approved :: MIT License
Classifier: Programming Language :: Python :: 3
Classifier: Programming Language :: Python :: 3.8
Classifier: Programming Language :: Python :: 3.9
Project-URL: Repository, https://gitlab.com/thesmiley1/gazoo.git
